pyarcgen/__init__.py
pyarcgen/config.py
pyarcgen/exception.py
pyarcgen/file.py
pyarcgen/gen.py
pyarcgen/gen_schema.py
pyarcgen/logger.py
pyarcgen/methods.py
pyarcgen/string.py
pyarcgen/utils.py
pyarcgen-0.0.1.dist-info/METADATA
pyarcgen-0.0.1.dist-info/WHEEL
pyarcgen-0.0.1.dist-info/top_level.txt
pyarcgen-0.0.1.dist-info/RECORD
