Metadata-Version: 2.1
Name: pyarcgen
Version: 0.0.1
Summary: Package permettant de generer un ensemble de fichiers et de fichier en fonction de la configuration voulu.
Author: BILONG NTOUBA Célestin
Author-email: bilongntouba.celestin@gmail.com
Keywords: python,hivi,pyarcgen,generator
Requires-Dist: jonschema ; python_version >= "0.0.9119"
Requires-Dist: pytz ; python_version >= "2022.1"
Requires-Dist: asyncio ; python_version >= "3.4.3"
Requires-Dist: typing ; python_version >= "3.7.4.3"
